antchain_sdk_ak_e3c3c9afe8cc46f7950be87f72fedc15/__init__.py
antchain_sdk_ak_e3c3c9afe8cc46f7950be87f72fedc15/client.py
antchain_sdk_ak_e3c3c9afe8cc46f7950be87f72fedc15/models.py
antchain_ak_e3c3c9afe8cc46f7950be87f72fedc15-1.0.0.dist-info/LICENSE
antchain_ak_e3c3c9afe8cc46f7950be87f72fedc15-1.0.0.dist-info/METADATA
antchain_ak_e3c3c9afe8cc46f7950be87f72fedc15-1.0.0.dist-info/WHEEL
antchain_ak_e3c3c9afe8cc46f7950be87f72fedc15-1.0.0.dist-info/top_level.txt
antchain_ak_e3c3c9afe8cc46f7950be87f72fedc15-1.0.0.dist-info/RECORD
